Metadata-Version: 1.1
Name: cmtimer
Version: 0.0.1
Summary: A simple context manager timing utility.
Home-page: http://github.org/wrwrwr/cmtimer
Author: Wojtek Ruszczewski
Author-email: python@wr.waw.pl
License: MIT
Platform: UNKNOWN
Classifier: Development Status :: 4 - Beta
Classifier: Intended Audience :: Developers
Classifier: Topic :: Utilities
Classifier: License :: OSI Approved :: MIT License
Classifier: Programming Language :: Python :: 3.4
Classifier: Programming Language :: Python :: 3.5
